awl/__init__.py
awl/core.py
awl/hitl.py
awl/jsonld_context.py
awl-0.3.2.dist-info/licenses/LICENSE
awl-0.3.2.dist-info/METADATA
awl-0.3.2.dist-info/WHEEL
awl-0.3.2.dist-info/top_level.txt
awl-0.3.2.dist-info/RECORD
