Metadata-Version: 2.4
Name: awl
Version: 0.3.2
Summary: Python implementation of the Abstract Workflow Language (AWL / AWL-LD)
Home-page: https://github.com/OO-LD/awl-python
Author: Simon Stier
Author-email: simon.stier@gmx.de
License: Apache-2.0
Project-URL: Documentation, https://oo-ld.github.io/awl-python/
Project-URL: Source, https://github.com/OO-LD/awl-python
Project-URL: Download, https://pypi.org/project/awl/#files
Platform: any
Classifier: Development Status :: 3 - Alpha
Classifier: Programming Language :: Python
License-File: LICENSE
Requires-Dist: ast2json
Requires-Dist: json2ast
Requires-Dist: pyyaml
Requires-Dist: pyld
Requires-Dist: rdflib
Requires-Dist: oold>=0.8.0
Provides-Extra: hitl
Requires-Dist: oold[UI-panel]; extra == "hitl"
Provides-Extra: dev
Requires-Dist: tox; extra == "dev"
Requires-Dist: pre-commit; extra == "dev"
Provides-Extra: testing
Requires-Dist: setuptools; extra == "testing"
Requires-Dist: pytest; extra == "testing"
Requires-Dist: pytest-cov; extra == "testing"
Requires-Dist: oold[UI-panel]; extra == "testing"
Dynamic: license-file
